{
  "tech": "Node.js + React + MCP servers (Perplexity, Filesystem, etc.), Vite, Jest, Redis, MongoDB",
  "keyDirs": {
    "src": [
      "api",
      "auth",
      "backend",
      "chat",
      "components",
      "config",
      "database",
      "frontend",
      "index.js",
      "mcp",
      "middleware",
      "ml",
      "mobile",
      "security",
      "server.js",
      "spotify",
      "utils"
    ],
    "scripts": [
      "README.md",
      "advanced-automation.js",
      "advanced_data_analysis.py",
      "analyze-automation-scripts.js",
      "analyze-json-data.js",
      "analyze-listening-history-merge.js",
      "analyze-missing-audio-features.js",
      "analyze-missing-data.js",
      "auth-wizard.js",
      "automation",
      "ci",
      "compare-databases.js",
      "complete-integrations.sh",
      "comprehensive-api-testing.js",
      "comprehensive-mcp-validation.js",
      "comprehensive-validation.js",
      "configure-redis-simple.js",
      "configure-redis.js",
      "continuous-agent.js",
      "continuous-mcp-monitor.js"
    ],
    "mcpServers": [
      "README.md",
      "analytics-server",
      "brave-search",
      "browserbase",
      "browserbase-client.js",
      "browserbase-cross-browser.js",
      "browserbase-orchestrator.js",
      "browserbase-test-config.json",
      "browserbase-workflows.js",
      "code-sandbox",
      "comprehensive-validator.js",
      "enhanced-browser-tools.js",
      "enhanced-file-utilities.js",
      "enhanced-mcp-performance-manager.js",
      "filescope-config.json",
      "filescope-handlers.js",
      "filescope-security.js",
      "mcp-integration-tester.js",
      "new-candidates",
      "package-management"
    ]
  },
  "mcp": "Perplexity MCP configured in .cursor/mcp.json with model llama-3.1-sonar-small-128k-online",
  "prompts": "Unified prompt catalog with executor and validator; added Perplexity analysis prompt"
}